qf-common/__init__.py
qf-common/data.py
qf-common/test.py
qf_common/__init__.py
qf_common/data.py
qf_common/package.py
qf_common/test.py
src/__init__.py
src/data.py
src/test.py
qf_common-0.6.dist-info/METADATA
qf_common-0.6.dist-info/WHEEL
qf_common-0.6.dist-info/top_level.txt
qf_common-0.6.dist-info/RECORD
