Metadata-Version: 2.1
Name: qf-common
Version: 0.6
Summary: Useful things for QF projects
Home-page: https://github.com/quality-first/qf-common
Author: Anton Stefanovich
Author-email: anton.stefanovich@gmail.com
License: MIT
Platform: UNKNOWN
